dlab/tg_sso/__init__.py
dlab_tg_sso-0.1.1.dist-info/METADATA
dlab_tg_sso-0.1.1.dist-info/WHEEL
dlab_tg_sso-0.1.1.dist-info/top_level.txt
dlab_tg_sso-0.1.1.dist-info/RECORD
