Metadata-Version: 2.4
Name: dlab-tg-sso
Version: 0.1.1
Summary: SDK для получения списка участников Telegram-чата
Author: 
License: MIT
Classifier: Programming Language :: Python :: 3
Classifier: Programming Language :: Python :: 3 :: Only
Classifier: Operating System :: OS Independent
Requires-Python: >=3.10
Requires-Dist: python-dotenv>=1.0.0
Requires-Dist: requests>=2.31.0
Dynamic: classifier
Dynamic: description
Dynamic: description-content-type
Dynamic: license
Dynamic: requires-dist
Dynamic: requires-python
Dynamic: summary
